{
  "metas": [
    {
      "id": "tt11417856",
      "type": "movie",
      "name": "The Deer King",
      "poster": "https://s4.anilist.co/file/anilistcdn/media/anime/cover/large/bx102891-lVsBWszCtTxd.jpg",
      "behaviorHints": {
        "defaultVideoId": "tt11417856"
      }
    },
    {
      "id": "tt14967958",
      "type": "movie",
      "name": "Goodbye, Don Glees!",
      "poster": "https://s4.anilist.co/file/anilistcdn/media/anime/cover/large/bx136302-4R03xBOGWrcq.jpg",
      "behaviorHints": {
        "defaultVideoId": "tt14967958"
      }
    },
    {
      "id": "tt15721650",
      "type": "movie",
      "name": "The Quintessential Quintuplets Movie",
      "poster": "https://s4.anilist.co/file/anilistcdn/media/anime/cover/large/bx131520-kCOY9XBAbMcX.png",
      "behaviorHints": {
        "defaultVideoId": "tt15721650"
      }
    },
    {
      "id": "tt14614892",
      "type": "movie",
      "name": "Dragon Ball Super: SUPER HERO",
      "poster": "https://s4.anilist.co/file/anilistcdn/media/anime/cover/large/bx133898-KdQ7fWTG06n4.png",
      "behaviorHints": {
        "defaultVideoId": "tt14614892"
      }
    },
    {
      "id": "tt16183464",
      "type": "movie",
      "name": "One Piece Film: Red",
      "poster": "https://s4.anilist.co/file/anilistcdn/media/anime/cover/large/bx141902-fTyoTk8F8qOl.jpg",
      "behaviorHints": {
        "defaultVideoId": "tt16183464"
      }
    },
    {
      "id": "tt17382524",
      "type": "movie",
      "name": "The Tunnel to Summer, the Exit of Goodbyes",
      "poster": "https://s4.anilist.co/file/anilistcdn/media/anime/cover/large/bx142769-kNyyqpwC9gGV.jpg",
      "behaviorHints": {
        "defaultVideoId": "tt17382524"
      }
    },
    {
      "id": "tt14364238",
      "type": "movie",
      "name": "Laid-Back Camp The Movie",
      "poster": "https://s4.anilist.co/file/anilistcdn/media/anime/cover/large/bx104460-EwUV9ZJMCtnR.jpg",
      "behaviorHints": {
        "defaultVideoId": "tt14364238"
      }
    },
    {
      "id": "tt10738536",
      "type": "movie",
      "name": "Delicious Party♡Precure: Yumemiru♡Okosama Lunch!",
      "poster": "https://s4.anilist.co/file/anilistcdn/media/anime/cover/large/bx144687-b2piUr5WSdYb.jpg",
      "behaviorHints": {
        "defaultVideoId": "tt10738536"
      }
    },
    {
      "id": "tt16428256",
      "type": "movie",
      "name": "Suzume",
      "poster": "https://s4.anilist.co/file/anilistcdn/media/anime/cover/large/bx142770-sG9FZa5JxlmE.jpg",
      "behaviorHints": {
        "defaultVideoId": "tt16428256"
      }
    },
    {
      "id": "tt15467380",
      "type": "movie",
      "name": "That Time I Got Reincarnated as a Slime the Movie: Scarlet Bond",
      "poster": "https://s4.anilist.co/file/anilistcdn/media/anime/cover/large/bx139498-DdVASeAj7ag4.jpg",
      "behaviorHints": {
        "defaultVideoId": "tt15467380"
      }
    },
    {
      "id": "tt15830702",
      "type": "movie",
      "name": "Sword Art Online the Movie -Progressive- Scherzo of Deep Night",
      "poster": "https://s4.anilist.co/file/anilistcdn/media/anime/cover/large/bx140999-8nRYAPkywhbl.jpg",
      "behaviorHints": {
        "defaultVideoId": "tt15830702"
      }
    },
    {
      "id": "tt15242330",
      "type": "movie",
      "name": "THE FIRST SLAM DUNK",
      "poster": "https://s4.anilist.co/file/anilistcdn/media/anime/cover/large/bx128207-IndYn57okYmk.jpg",
      "behaviorHints": {
        "defaultVideoId": "tt15242330"
      }
    }
  ]
}